setup.py
ppp_libmodule/__init__.py
ppp_libmodule/config.py
ppp_libmodule/exceptions.py
ppp_libmodule/http.py
ppp_libmodule/shortcuts.py
ppp_libmodule/simplification.py
ppp_libmodule/tests.py
ppp_libmodule.egg-info/PKG-INFO
ppp_libmodule.egg-info/SOURCES.txt
ppp_libmodule.egg-info/dependency_links.txt
ppp_libmodule.egg-info/requires.txt
ppp_libmodule.egg-info/top_level.txt