Metadata-Version: 1.1
Name: ppp-libmodule
Version: 0.7.7
Summary: Library for writing Python modules for the PPP.
Home-page: https://github.com/ProjetPP/PPP-libmodule-Python
Author: Valentin Lorentz
Author-email: valentin.lorentz+ppp@ens-lyon.org
License: MIT
Platform: UNKNOWN
Classifier: Environment :: No Input/Output (Daemon)
Classifier: Development Status :: 1 - Planning
Classifier: Intended Audience :: Developers
Classifier: License :: OSI Approved :: MIT License
Classifier: Operating System :: OS Independent
Classifier: Programming Language :: Python :: 3
Classifier: Programming Language :: Python :: 3.2
Classifier: Programming Language :: Python :: 3.3
Classifier: Programming Language :: Python :: 3.4
Classifier: Topic :: Internet :: WWW/HTTP :: WSGI :: Application
Classifier: Topic :: Software Development :: Libraries
